kiali/__init__.py
kiali/api_connector.py
kiali/client.py
kiali/swagger.py
kiali_client-0.9.3.dist-info/AUTHORS
kiali_client-0.9.3.dist-info/LICENSE.txt
kiali_client-0.9.3.dist-info/METADATA
kiali_client-0.9.3.dist-info/WHEEL
kiali_client-0.9.3.dist-info/pbr.json
kiali_client-0.9.3.dist-info/top_level.txt
kiali_client-0.9.3.dist-info/RECORD
