Metadata-Version: 2.1
Name: kiali-client
Version: 0.9.3
Summary: Python client to communicate with Kiali server over HTTP(S)
Home-page: https://github.com/kiali/kiali-client-python
Author: Guilherme Baufaker Rego
Author-email: "gbaufake@redhat.com
License: Apache License 2.0
Keywords: kiali,service-mesh,istio,kurbenetes,openshift
Platform: UNKNOWN
Classifier: Development Status :: 5 - Production/Stable
Classifier: Intended Audience :: Developers
Classifier: Programming Language :: Python
Classifier: Programming Language :: Python :: 3
Classifier: Topic :: System :: Monitoring
Requires: pbr
